[
  {
    "command": "force:package1:version:create",
    "plugin": "@salesforce/plugin-packaging",
    "flags": [
      "apiversion",
      "description",
      "installationkey",
      "json",
      "loglevel",
      "managedreleased",
      "name",
      "packageid",
      "postinstallurl",
      "releasenotesurl",
      "targetusername",
      "version",
      "wait"
    ],
    "alias": ["force:package1:beta:version:create"]
  },
  {
    "command": "force:package1:version:create:get",
    "plugin": "@salesforce/plugin-packaging",
    "flags": ["apiversion", "json", "loglevel", "requestid", "targetusername"],
    "alias": ["force:package1:beta:version:create:get"]
  },
  {
    "command": "force:package1:version:display",
    "plugin": "@salesforce/plugin-packaging",
    "flags": ["apiversion", "json", "loglevel", "packageversionid", "targetusername"],
    "alias": ["force:package1:beta:version:display"]
  },
  {
    "command": "force:package1:version:list",
    "plugin": "@salesforce/plugin-packaging",
    "flags": ["apiversion", "json", "loglevel", "packageid", "targetusername"],
    "alias": ["force:package1:beta:version:list"]
  },
  {
    "command": "force:package:convert",
    "plugin": "@salesforce/plugin-packaging",
    "flags": [
      "apiversion",
      "buildinstance",
      "definitionfile",
      "installationkey",
      "installationkeybypass",
      "json",
      "loglevel",
      "package",
      "seedmetadata",
      "targetdevhubusername",
      "wait"
    ],
    "alias": ["force:package:beta:convert"]
  },
  {
    "command": "force:package:create",
    "plugin": "@salesforce/plugin-packaging",
    "flags": [
      "apiversion",
      "description",
      "errornotificationusername",
      "json",
      "loglevel",
      "name",
      "nonamespace",
      "orgdependent",
      "packagetype",
      "path",
      "targetdevhubusername"
    ],
    "alias": ["force:package:beta:create"]
  },
  {
    "command": "force:package:delete",
    "plugin": "@salesforce/plugin-packaging",
    "flags": ["apiversion", "json", "loglevel", "noprompt", "package", "targetdevhubusername", "undelete"],
    "alias": ["force:package:beta:delete"]
  },
  {
    "command": "force:package:install",
    "plugin": "@salesforce/plugin-packaging",
    "flags": [
      "apexcompile",
      "apiversion",
      "installationkey",
      "json",
      "loglevel",
      "noprompt",
      "package",
      "publishwait",
      "securitytype",
      "targetusername",
      "upgradetype",
      "wait"
    ],
    "alias": ["force:package:beta:install"]
  },
  {
    "command": "force:package:install:report",
    "plugin": "@salesforce/plugin-packaging",
    "flags": ["apiversion", "json", "loglevel", "requestid", "targetusername"],
    "alias": ["force:package:beta:install:report"]
  },
  {
    "command": "force:package:installed:list",
    "plugin": "@salesforce/plugin-packaging",
    "flags": ["apiversion", "json", "loglevel", "targetusername"],
    "alias": ["force:package:beta:installed:list"]
  },
  {
    "command": "force:package:list",
    "plugin": "@salesforce/plugin-packaging",
    "flags": ["apiversion", "json", "loglevel", "targetdevhubusername", "verbose"],
    "alias": ["force:package:beta:list"]
  },
  {
    "command": "force:package:uninstall",
    "plugin": "@salesforce/plugin-packaging",
    "flags": ["apiversion", "json", "loglevel", "package", "targetusername", "wait"],
    "alias": ["force:package:beta:uninstall"]
  },
  {
    "command": "force:package:uninstall:report",
    "plugin": "@salesforce/plugin-packaging",
    "flags": ["apiversion", "json", "loglevel", "requestid", "targetusername"],
    "alias": ["force:package:beta:uninstall:report"]
  },
  {
    "command": "force:package:update",
    "plugin": "@salesforce/plugin-packaging",
    "flags": [
      "apiversion",
      "description",
      "errornotificationusername",
      "json",
      "loglevel",
      "name",
      "package",
      "targetdevhubusername"
    ],
    "alias": ["force:package:beta:update"]
  },
  {
    "command": "force:package:version:create",
    "plugin": "@salesforce/plugin-packaging",
    "flags": [
      "apiversion",
      "branch",
      "buildinstance",
      "codecoverage",
      "definitionfile",
      "installationkey",
      "installationkeybypass",
      "json",
      "language",
      "loglevel",
      "package",
      "path",
      "postinstallscript",
      "postinstallurl",
      "preserve",
      "releasenotesurl",
      "skipancestorcheck",
      "skipvalidation",
      "tag",
      "targetdevhubusername",
      "uninstallscript",
      "validateschema",
      "versiondescription",
      "versionname",
      "versionnumber",
      "wait"
    ],
    "alias": ["force:package:beta:version:create"]
  },
  {
    "command": "force:package:version:create:list",
    "plugin": "@salesforce/plugin-packaging",
    "flags": ["apiversion", "createdlastdays", "json", "loglevel", "status", "targetdevhubusername"],
    "alias": ["force:package:beta:version:create:list"]
  },
  {
    "command": "force:package:version:create:report",
    "plugin": "@salesforce/plugin-packaging",
    "flags": ["apiversion", "json", "loglevel", "packagecreaterequestid", "targetdevhubusername"],
    "alias": ["force:package:beta:version:create:report"]
  },
  {
    "command": "force:package:version:delete",
    "plugin": "@salesforce/plugin-packaging",
    "flags": ["apiversion", "json", "loglevel", "noprompt", "package", "targetdevhubusername", "undelete"],
    "alias": ["force:package:beta:version:delete"]
  },
  {
    "command": "force:package:version:displayancestry",
    "plugin": "@salesforce/plugin-packaging",
    "flags": ["apiversion", "dotcode", "json", "loglevel", "package", "targetdevhubusername", "verbose"],
    "alias": ["force:package:beta:version:displayancestry"]
  },
  {
    "command": "force:package:version:list",
    "plugin": "@salesforce/plugin-packaging",
    "flags": [
      "apiversion",
      "concise",
      "createdlastdays",
      "json",
      "loglevel",
      "modifiedlastdays",
      "orderby",
      "packages",
      "released",
      "targetdevhubusername",
      "verbose"
    ],
    "alias": ["force:package:beta:version:list"]
  },
  {
    "command": "force:package:version:promote",
    "plugin": "@salesforce/plugin-packaging",
    "flags": ["apiversion", "json", "loglevel", "noprompt", "package", "targetdevhubusername"],
    "alias": ["force:package:beta:version:promote"]
  },
  {
    "command": "force:package:version:report",
    "plugin": "@salesforce/plugin-packaging",
    "flags": ["apiversion", "json", "loglevel", "package", "targetdevhubusername", "verbose"],
    "alias": ["force:package:beta:version:report"]
  },
  {
    "command": "force:package:version:update",
    "plugin": "@salesforce/plugin-packaging",
    "flags": [
      "apiversion",
      "branch",
      "installationkey",
      "json",
      "loglevel",
      "package",
      "tag",
      "targetdevhubusername",
      "versiondescription",
      "versionname"
    ],
    "alias": ["force:package:beta:version:update"]
  }
]
